basis_vm/__init__.py
basis_vm/config/__init__.py
basis_vm/config/db.py
basis_vm/config/env.py
basis_vm/config/logging.py
basis_vm/contract/__init__.py
basis_vm/contract/call.py
basis_vm/contract/deploy.py
basis_vm/contract/management.py
basis_vm/execution/__init__.py
basis_vm/execution/sandbox.py
basis_vm/interfaces/IBNS20.py
basis_vm/interfaces/IBNS721.py
basis_vm/interfaces/IBNS721Enumerable.py
basis_vm/interfaces/__init__.py
basis_vm/security/__init__.py
basis_vm/security/decorators.py
basis_vm/security/safe_import.py
basis_vm/security/validation.py
basis_vm/utils/__init__.py
basis_vm/utils/constants.py
basis_vm/utils/serialization.py
tests/__init__.py
tests/config/__init__.py
tests/config/test_db.py
tests/config/test_env.py
tests/config/test_logging.py
tests/contract/__init__.py
tests/contract/test_call.py
tests/contract/test_deploy.py
tests/contract/test_management.py
tests/execution/__init__.py
tests/execution/test_sandbox.py
tests/security/__init__.py
tests/security/test_decorators.py
tests/security/test_safe_import.py
tests/security/test_validation.py
tests/utils/__init__.py
tests/utils/test_constants.py
tests/utils/test_serialization.py
basis_vm-0.1.2.dist-info/LICENSE
basis_vm-0.1.2.dist-info/METADATA
basis_vm-0.1.2.dist-info/WHEEL
basis_vm-0.1.2.dist-info/top_level.txt
basis_vm-0.1.2.dist-info/RECORD
