Metadata-Version: 2.1
Name: basis-vm
Version: 0.1.2
Summary: A complete Python virtual machine for executing smart contracts.
Home-page: https://bitbucket.org/base-computing/basis_vm
Author: BASE COMPUTING S.A.S.
Author-email: social@basecomputing.com.co
Classifier: Programming Language :: Python :: 3
Classifier: License :: OSI Approved :: MIT License
Classifier: Operating System :: OS Independent
Requires-Python: >=3.9
License-File: LICENSE
Requires-Dist: pymongo==4.1.1
